<?xml version="1.0" encoding="utf-8" ?>
<dwsync>
<file name="dice.gif" server="C:/wamp/www/" local="128508105660000000" remote="128508105660000000" />
<file name="dice1.gif" server="C:/wamp/www/" local="128508121400000000" remote="128508121400000000" />
<file name="dice2.gif" server="C:/wamp/www/" local="128508121740000000" remote="128508121740000000" />
<file name="dice3.gif" server="C:/wamp/www/" local="128508122320000000" remote="128508122320000000" />
<file name="dice4.gif" server="C:/wamp/www/" local="128508122820000000" remote="128508122820000000" />
<file name="dice5.gif" server="C:/wamp/www/" local="128508123000000000" remote="128508123000000000" />
<file name="dice6.gif" server="C:/wamp/www/" local="128508123640000000" remote="128508123640000000" />
<file name="Thumbs.db" server="C:/wamp/www/" local="128508400840000000" remote="128508400840000000" />
</dwsync>